invoicing/__init__.py
invoicing/invoice.py
any_excel_2_pdf-1.0.1.dist-info/METADATA
any_excel_2_pdf-1.0.1.dist-info/WHEEL
any_excel_2_pdf-1.0.1.dist-info/top_level.txt
any_excel_2_pdf-1.0.1.dist-info/RECORD
