Metadata-Version: 2.4
Name: any-excel-2-pdf
Version: 1.0.1
Summary: Convert Excel invoices to PDF invoices.
Author-email: Doron Levin <doronlvn@gmail.com>
License: MIT
Project-URL: Homepage, https://example.com
Keywords: invoice,excel,pdf
Classifier: Development Status :: 3 - Alpha
Classifier: Intended Audience :: Developers
Classifier: Topic :: Software Development :: Build Tools
Classifier: License :: OSI Approved :: MIT License
Classifier: Programming Language :: Python :: 3.8
Classifier: Programming Language :: Python :: 3.9
Classifier: Programming Language :: Python :: 3.10
Classifier: Programming Language :: Python :: 3.11
Classifier: Programming Language :: Python :: 3.13
Requires-Python: >=3.8
Requires-Dist: pandas
Requires-Dist: fpdf
Requires-Dist: openpyxl
